shapelets_rec/__init__.py
shapelets_rec/_client.py
shapelets_rec/_extractor.py
shapelets_rec/_native.py
shapelets_rec/_native.pyi
shapelets_rec/_observers.py
shapelets_rec/_scanner.py
shapelets_rec/_shapelets_rec_extension.cp310-win_amd64.pyd
shapelets_rec/_shapelets_rec_server_extension.cp310-win_amd64.pyd
shapelets_rec/_version.py
shapelets_rec/_version.pyi
shapelets_rec/py.typed
shapelets_rec_client-0.1.dev1.dist-info/LICENSE.md
shapelets_rec_client-0.1.dev1.dist-info/METADATA
shapelets_rec_client-0.1.dev1.dist-info/WHEEL
shapelets_rec_client-0.1.dev1.dist-info/top_level.txt
shapelets_rec_client-0.1.dev1.dist-info/RECORD
