Metadata-Version: 2.1
Name: shapelets-rec-client
Version: 0.1.dev1
Summary: Shapelets REC Client Library
Home-page: https://shapelets.io
Author: Shapelets.io
Author-email: dev@shapelets.io
Maintainer: Shapelets Dev Team
Maintainer-email: info@shapelets.io
Project-URL: Homepage, https://shapelets.io/
Project-URL: Documentation, https://shapelets.io/doc/contents.html
Platform: Any
Classifier: Programming Language :: Python :: 3
Classifier: Operating System :: Microsoft :: Windows
Classifier: Operating System :: Unix
Classifier: License :: Other/Proprietary License
Requires-Python: >=3.7
License-File: LICENSE.md
Requires-Dist: tqdm (>=4.64.1)
Requires-Dist: pyzmq (~=24.0.1)
Requires-Dist: pydantic (~=1.10.2)
Requires-Dist: pyarrow (~=11.0.0)
Requires-Dist: typing-extensions (~=4.2.0)
Requires-Dist: orjson (~=3.8.2)
Requires-Dist: requests (~=2.28.2)
Requires-Dist: rodi (~=1.1.3)
Provides-Extra: docs
Requires-Dist: Sphinx (>=4.4.0) ; extra == 'docs'
Requires-Dist: myst-parser (>=0.13) ; extra == 'docs'
Requires-Dist: sphinx-rtd-theme (>=1.0.0) ; extra == 'docs'
Requires-Dist: sphinxcontrib-applehelp (>=1.0.2) ; extra == 'docs'
Requires-Dist: sphinxcontrib-devhelp (>=1.0.2) ; extra == 'docs'
Requires-Dist: sphinxcontrib-htmlhelp (>=2.0.0) ; extra == 'docs'
Requires-Dist: sphinxcontrib-jsmath (>=1.0.1) ; extra == 'docs'
Requires-Dist: sphinxcontrib-qthelp (>=1.0.3) ; extra == 'docs'
Requires-Dist: sphinxcontrib-serializinghtml (>=1.1.5) ; extra == 'docs'
Provides-Extra: influx
Requires-Dist: line-protocol-parser (~=1.1.1) ; extra == 'influx'
